billiards/__init__.py
billiards/obstacles.py
billiards/physics.py
billiards/simulation.py
billiards/visualize.py
billiards-0.5.0.dist-info/LICENSE
billiards-0.5.0.dist-info/METADATA
billiards-0.5.0.dist-info/WHEEL
billiards-0.5.0.dist-info/top_level.txt
billiards-0.5.0.dist-info/RECORD
