Metadata-Version: 2.1
Name: billiards
Version: 0.5.0
Summary: A 2D physics engine for simulating dynamical billiards
Home-page: https://github.com/markus-ebke/python-billiards
Author: Markus Ebke
Author-email: markus.ebke92@gmail.com
License: GNU General Public License v3 or later (GPLv3+)
Project-URL: Source Code, https://github.com/markus-ebke/python-billiards
Project-URL: Bug Reports, https://github.com/markus-ebke/python-billiards/issues
Keywords: python3,physics-engine,physics-2d
Platform: any
Classifier: Development Status :: 3 - Alpha
Classifier: Intended Audience :: Developers
Classifier: Intended Audience :: Education
Classifier: Intended Audience :: Science/Research
Classifier: License :: OSI Approved
Classifier: License :: OSI Approved :: GNU General Public License (GPL)
Classifier: License :: OSI Approved :: GNU General Public License v3 or later (GPLv3+)
Classifier: Operating System :: OS Independent
Classifier: Natural Language :: English
Classifier: Programming Language :: Python
Classifier: Programming Language :: Python :: 3
Classifier: Programming Language :: Python :: 3 :: Only
Classifier: Programming Language :: Python :: 3.7
Classifier: Programming Language :: Python :: 3.8
Classifier: Programming Language :: Python :: 3.9
Classifier: Programming Language :: Python :: 3.10
Classifier: Programming Language :: Python :: Implementation :: CPython
Classifier: Topic :: Education
Classifier: Topic :: Scientific/Engineering
Classifier: Topic :: Scientific/Engineering :: Physics
Classifier: Topic :: Software Development :: Libraries
Classifier: Topic :: Software Development :: Libraries :: Python Modules
Requires-Python: >=3.7
License-File: LICENSE
Requires-Dist: numpy
Provides-Extra: visualize
Requires-Dist: matplotlib ; extra == 'visualize'
Requires-Dist: tqdm ; extra == 'visualize'
Requires-Dist: pyglet ; extra == 'visualize'
